json2img/__init__.py
json2img/__main__.py
json2img/src/__init__.py
json2img/src/json_to_image.py
json2img-0.1.2.dist-info/LICENSE.txt
json2img-0.1.2.dist-info/METADATA
json2img-0.1.2.dist-info/WHEEL
json2img-0.1.2.dist-info/top_level.txt
json2img-0.1.2.dist-info/RECORD
