Metadata-Version: 2.1
Name: json2img
Version: 0.1.2
Summary: Generate randomly colored images from Label Studio annotations
Author-email: Ujan RoyBandyopadhyay <ujan.roybandyopadhyay@gmail.com>
Classifier: Programming Language :: Python :: 3
Classifier: Programming Language :: Python :: 3.7
Classifier: Programming Language :: Python :: 3.8
Classifier: Programming Language :: Python :: 3.9
Classifier: Programming Language :: Python :: 3.10
Classifier: License :: OSI Approved :: MIT License
Requires-Python: >=3.7
License-File: LICENSE.txt
Requires-Dist: pygame (>=2.0.0)
